phygitalism_logger/__init__.py
phygitalism_logger/config.py
phygitalism_logger/generate.py
phygitalism_logger/setup.py
phygitalism_logger-0.1.4.dist-info/entry_points.txt
phygitalism_logger-0.1.4.dist-info/WHEEL
phygitalism_logger-0.1.4.dist-info/METADATA
phygitalism_logger-0.1.4.dist-info/RECORD
