Metadata-Version: 2.1
Name: phygitalism-logger
Version: 0.1.4
Summary: 
Author: Phygitalism
Requires-Python: >=3.7,<4.0
Classifier: Programming Language :: Python :: 3
Classifier: Programming Language :: Python :: 3.7
Classifier: Programming Language :: Python :: 3.8
Classifier: Programming Language :: Python :: 3.9
Requires-Dist: phygitalism-config (>=0.1.11,<0.2.0)
Requires-Dist: pygelf (>=0.4.0,<0.5.0)
